graphlib/__init__.py
graphlib/algorithms.py
graphlib/dump.py
graphlib/graph.py
graphlib/jsondef.py
graphlib/util.py
python_graph_alg_lib-1.0.0.dist-info/LICENSE
python_graph_alg_lib-1.0.0.dist-info/METADATA
python_graph_alg_lib-1.0.0.dist-info/WHEEL
python_graph_alg_lib-1.0.0.dist-info/top_level.txt
python_graph_alg_lib-1.0.0.dist-info/RECORD
