Metadata-Version: 2.1
Name: python-graph-alg-lib
Version: 1.0.0
Summary: Library of Graph Algorithms for Python
Home-page: https://github.com/Jardo72/python-graph-alg-lib
Author: Jaroslav Chmurny
Author-email: jaroslav.chmurny@gmail.com
License: UNKNOWN
Platform: UNKNOWN
Classifier: Programming Language :: Python :: 3
Classifier: License :: OSI Approved :: Apache Software License
Classifier: Operating System :: OS Independent
Classifier: Typing :: Typed
Classifier: Topic :: Software Development :: Libraries
Classifier: Topic :: Education
Requires-Python: >=3.8
